Metadata-Version: 2.1
Name: notifbot
Version: 0.1
Summary: send notification via Slack
Home-page: https://github.com/tristanmsct/Notifier
Author: Tristan Muscat
Author-email: traistan.muscat@gmail.com
License: MIT
Platform: unix
Platform: linux
Platform: osx
Platform: cygwin
Platform: win32
Classifier: Programming Language :: Python :: 3
Classifier: Programming Language :: Python :: 3 :: Only
Classifier: Programming Language :: Python :: 3.6
Classifier: Programming Language :: Python :: 3.7
Classifier: Programming Language :: Python :: 3.8
Classifier: Programming Language :: Python :: 3.9
Requires-Python: >=3.6
Provides-Extra: testing
